.coveragerc
.editorconfig
.gitignore
.travis.yml
AUTHORS.rst
CONTRIBUTING.rst
HISTORY.rst
LICENSE
MANIFEST.in
Makefile
README.rst
manage.py
requirements.txt
requirements_dev.txt
requirements_test.txt
runtests.py
setup.cfg
setup.py
tox.ini
.github/ISSUE_TEMPLATE.md
django_flexible_filter_conditions.egg-info/PKG-INFO
django_flexible_filter_conditions.egg-info/SOURCES.txt
django_flexible_filter_conditions.egg-info/dependency_links.txt
django_flexible_filter_conditions.egg-info/not-zip-safe
django_flexible_filter_conditions.egg-info/top_level.txt
docs/Makefile
docs/authors.rst
docs/conf.py
docs/contributing.rst
docs/history.rst
docs/index.rst
docs/installation.rst
docs/make.bat
docs/readme.rst
docs/usage.rst
flexible_filter_conditions/.models.py.swn
flexible_filter_conditions/.models.py.swo
flexible_filter_conditions/__init__.py
flexible_filter_conditions/admin.py
flexible_filter_conditions/admin_filters.py
flexible_filter_conditions/apps.py
flexible_filter_conditions/models.py
flexible_filter_conditions/migrations/0001_initial.py
flexible_filter_conditions/migrations/0002_auto_20200218_1214.py
flexible_filter_conditions/migrations/0003_auto_20200218_1236.py
flexible_filter_conditions/migrations/__init__.py
flexible_filter_conditions/templates/flexible_filters/base.html
flexible_filter_conditions/test_utils/__init__.py
flexible_filter_conditions/test_utils/test_app/__init__.py
flexible_filter_conditions/test_utils/test_app/admin.py
flexible_filter_conditions/test_utils/test_app/apps.py
flexible_filter_conditions/test_utils/test_app/models.py
flexible_filter_conditions/test_utils/test_app/migrations/0001_initial.py
flexible_filter_conditions/test_utils/test_app/migrations/__init__.py
tests/README.md
tests/__init__.py
tests/requirements.txt
tests/settings.py
tests/test_filters.py
tests/test_models.py
tests/test_terminal_condition.py
tests/urls.py