Metadata-Version: 1.1
Name: django-flexible-filter-conditions
Version: 0.5.0
Summary: Flexible query filter conditions, that can be defined from django-admin and used for segmentation of date (i.e. Profiles).
Home-page: https://github.com/PetrDlouhy/django-flexible-filter-conditions
Author: Petr Dlouhý
Author-email: petr.dlouhy@email.cz
License: MIT
Keywords: django-flexible-filter-conditions
Platform: UNKNOWN
Classifier: Development Status :: 3 - Alpha
Classifier: Framework :: Django :: 1.11
Classifier: Framework :: Django :: 2.1
Classifier: Intended Audience :: Developers
Classifier: License :: OSI Approved :: BSD License
Classifier: Natural Language :: English
Classifier: Programming Language :: Python :: 2
Classifier: Programming Language :: Python :: 2.7
Classifier: Programming Language :: Python :: 3
Classifier: Programming Language :: Python :: 3.5
Classifier: Programming Language :: Python :: 3.6
